chanim/__init__.py
chanim/chem_anims.py
chanim/chem_objects.py
chanim/compounds.py
chanim/templates.py
chanim/utils.py
chanim-1.3.dist-info/entry_points.txt
chanim-1.3.dist-info/LICENSE
chanim-1.3.dist-info/WHEEL
chanim-1.3.dist-info/METADATA
chanim-1.3.dist-info/RECORD
