Metadata-Version: 2.1
Name: chanim
Version: 1.3
Summary: Manim extension for making chemistry videos
Home-page: https://github.com/raghavg123/chanim
License: MIT
Keywords: chemistry,animation,manim
Author: kilacoda
Author-email: kilacoda@gmail.com
Requires-Python: >=3.7,<4.0
Classifier: License :: OSI Approved :: MIT License
Classifier: Programming Language :: Python :: 3
Classifier: Programming Language :: Python :: 3.10
Classifier: Programming Language :: Python :: 3.7
Classifier: Programming Language :: Python :: 3.8
Classifier: Programming Language :: Python :: 3.9
Requires-Dist: manim
Project-URL: Repository, https://github.com/raghavg123/chanim
